MANIFEST.in
README.rst
setup.py
bin/fun
funny/__init__.py
funny.egg-info/PKG-INFO
funny.egg-info/SOURCES.txt
funny.egg-info/dependency_links.txt
funny.egg-info/not-zip-safe
funny.egg-info/requires.txt
funny.egg-info/top_level.txt