Metadata-Version: 1.0
Name: funny
Version: 0.1
Summary: Demo of package
Home-page: UNKNOWN
Author: Christina
Author-email: beemerchristina@gmail.com
License: MIT
Platform: UNKNOWN
